MANIFEST.in
README.rst
requirements.txt
setup.py
test-requirements.txt
docs/LICENSE
tests/__init__.py
tests/__init__.pyc
tests/connection_tests.py
tests/connection_tests.pyc
tests/customer_tests.py
tests/customer_tests.pyc
tests/reports_tests.py
tests/reports_tests.pyc
tests/rules_tests.py
tests/rules_tests.pyc
tests/vcenter_tests.py
tests/vcenter_tests.pyc
tests/vcloud_director_tests.py
tests/vcloud_director_tests.pyc
tests/__pycache__/__init__.cpython-33.pyc
tests/__pycache__/connection_tests.cpython-33.pyc
tests/__pycache__/customer_tests.cpython-33.pyc
tests/__pycache__/reports_tests.cpython-33.pyc
tests/__pycache__/rules_tests.cpython-33.pyc
tests/__pycache__/vcenter_tests.cpython-33.pyc
tests/fixtures/create_duplicate_rule.yaml
tests/fixtures/create_new_customer.yaml
tests/fixtures/create_new_customer_duplicate_bad_request.yaml
tests/fixtures/create_new_customer_no_country_code.yaml
tests/fixtures/create_new_customer_using_country_name.yaml
tests/fixtures/create_new_rule.yaml
tests/fixtures/create_new_rule_elements_out_of_order_403.yaml
tests/fixtures/create_new_rule_end_of_input_403.yaml
tests/fixtures/create_new_rule_fail_no_customer.yaml
tests/fixtures/create_vcd_success.yaml
tests/fixtures/create_vcenter.yaml
tests/fixtures/delete_customer.yaml
tests/fixtures/delete_rule_by_id.yaml
tests/fixtures/delete_rule_by_id_not_found.yaml
tests/fixtures/get_all_customers.yaml
tests/fixtures/get_all_rules.yaml
tests/fixtures/get_all_vcenters.yaml
tests/fixtures/get_all_vcenters_not_found.yaml
tests/fixtures/get_customer.yaml
tests/fixtures/get_customer_not_found.yaml
tests/fixtures/get_customer_rules.yaml
tests/fixtures/get_report_by_id.yaml
tests/fixtures/get_report_by_id_bad_request.yaml
tests/fixtures/get_report_list.yaml
tests/fixtures/get_rule_by_id_found.yaml
tests/fixtures/get_rule_by_id_not_found.yaml
tests/fixtures/get_vcenter_by_id_found.yaml
tests/fixtures/get_vcenter_by_id_not_found.yaml
tests/fixtures/update_customer_name.yaml
thunderhead/__init__.py
thunderhead.egg-info/PKG-INFO
thunderhead.egg-info/SOURCES.txt
thunderhead.egg-info/dependency_links.txt
thunderhead.egg-info/requires.txt
thunderhead.egg-info/top_level.txt
thunderhead.egg-info/zip-safe
